einsum_benchmark-0.1.7.dist-info/METADATA
einsum_benchmark-0.1.7.dist-info/WHEEL
einsum_benchmark-0.1.7.dist-info/licenses/LICENSE
einsum_benchmark/.DS_Store
einsum_benchmark/__init__.py
einsum_benchmark/converters/__init__.py
einsum_benchmark/converters/graphical_model.py
einsum_benchmark/converters/model_counting.py
einsum_benchmark/generators/.DS_Store
einsum_benchmark/generators/__init__.py
einsum_benchmark/generators/language_model/__init__.py
einsum_benchmark/generators/language_model/architecture.py
einsum_benchmark/generators/language_model/generator.py
einsum_benchmark/generators/language_model/symbols.py
einsum_benchmark/generators/quantum_computing/__init__.py
einsum_benchmark/generators/quantum_computing/maxcut.py
einsum_benchmark/generators/quantum_computing/mps_product.py
einsum_benchmark/generators/random/__init__.py
einsum_benchmark/generators/random/connected_hypernetwork.py
einsum_benchmark/generators/random/connected_network.py
einsum_benchmark/generators/random/randreg.py
einsum_benchmark/generators/random/util.py
einsum_benchmark/generators/structured/__init__.py
einsum_benchmark/generators/structured/lattice.py
einsum_benchmark/generators/structured/matrix_chain.py
einsum_benchmark/generators/structured/tree.py
einsum_benchmark/instances.py
einsum_benchmark/meta/__init__.py
einsum_benchmark/meta/info.py
einsum_benchmark/meta/kahypar_profiles/cut_kKaHyPar_sea20.ini
einsum_benchmark/meta/kahypar_profiles/cut_rKaHyPar_sea20.ini
einsum_benchmark/meta/kahypar_profiles/km1_kKaHyPar_sea20.ini
einsum_benchmark/meta/kahypar_profiles/km1_rKaHyPar_sea20.ini
einsum_benchmark/meta/kahypar_profiles/old/cut_kKaHyPar_sea20.ini
einsum_benchmark/meta/kahypar_profiles/old/cut_rKaHyPar_sea20.ini
einsum_benchmark/meta/kahypar_profiles/old/km1_kKaHyPar_sea20.ini
einsum_benchmark/meta/kahypar_profiles/old/km1_rKaHyPar_sea20.ini
einsum_benchmark/meta/metadata.xlsx
einsum_benchmark/meta/path_finder.py
einsum_benchmark/meta/runtime.py
einsum_benchmark/util.py
einsum_benchmark-0.1.7.dist-info/RECORD
