Metadata-Version: 2.1
Name: einsum_benchmark
Version: 0.1.7
Summary: Wrapper package for the einsum benchmark dataset and code to create new instances of the various types used in the benchmark
Author-Email: Christoph Staudt <christoph.staudt@uni-jena.de>, Mark Blacher <mark.blacher@uni-jena.de>, Maurice Wenig <maurice.wenig@uni-jena.de>, Niklas Merk <niklas.merk@uni-jena.de>
License: MIT
Requires-Python: >=3.10
Requires-Dist: numpy>=1.26.4
Requires-Dist: opt-einsum>=3.3.0
Requires-Dist: pooch>=1.8.1
Requires-Dist: pandas>=2.2.2; extra == "util"
Requires-Dist: openpyxl>=3.1.3; extra == "util"
Requires-Dist: networkx>=3.3; extra == "generators"
Requires-Dist: quimb>=1.8.1; extra == "generators"
Requires-Dist: cgreedy>=0.0.2; extra == "path"
Requires-Dist: kahypar>=1.3.5; extra == "path"
Requires-Dist: optuna>=3.6.1; extra == "path"
Provides-Extra: util
Provides-Extra: generators
Provides-Extra: path
